README.md
setup.py
GB_code.egg-info/PKG-INFO
GB_code.egg-info/SOURCES.txt
GB_code.egg-info/dependency_links.txt
GB_code.egg-info/entry_points.txt
GB_code.egg-info/requires.txt
GB_code.egg-info/top_level.txt
gb_code/__init__.py
gb_code/csl_generator.py
gb_code/gb_generator.py