Metadata-Version: 1.2
Name: GB-code
Version: 1.0.0
Summary: A GB generation code
Home-page: https://github.com/oekosheri/GB_code
Author: R.Hadian
Author-email: shahrzadhadian@gmail.com
License: LICENSE
Platform: UNKNOWN
Requires-Python: >3.5.1
